MANIFEST.in
README.rst
setup.cfg
setup.py
ashell/__init__.py
ashell/adbrc
ashell/ashell.py
ashell.egg-info/PKG-INFO
ashell.egg-info/SOURCES.txt
ashell.egg-info/dependency_links.txt
ashell.egg-info/entry_points.txt
ashell.egg-info/requires.txt
ashell.egg-info/top_level.txt